py_kms_api/__init__.py
py_kms_api/definitions.py
py_kms_api-2.0.0.dist-info/LICENSE
py_kms_api-2.0.0.dist-info/METADATA
py_kms_api-2.0.0.dist-info/WHEEL
py_kms_api-2.0.0.dist-info/RECORD
